[{"status":"ok","code":200,"message":"The request succeeded.","data":[{"results":[{"authors":"Sebastien Rousseau","date":"2021-05-25 19:45:18 +0100","description":"A responsive CSS grid using flexbox for desktop, tablet and mobile viewports.","id":"ff9b191a-b2a608ba3475-40a1-660d-b2a608ba3475","image":"/assets/images/backgrounds/bg-grid-system.png","keywords":"12column, columns, container, css, cssflexbox, cssgrid, cssgridsystem, flexbox, framework, front-end, frontend, fullyresponsive, gridsystem, light-weight, mobile-first, modern, responsive, robust, rows, semantic, simplecssgridsystem, skeletonic, skeletonic.css","subtitle":"A fully responsive, 12 column grid-based layout system making it easier to design web pages.","title":"Grid System","url":"/grid-system.html"}]}]}]